deciphon_api/__init__.py
deciphon_api/api/__init__.py
deciphon_api/api/api.py
deciphon_api/api/authentication.py
deciphon_api/api/dbs.py
deciphon_api/api/hmms.py
deciphon_api/api/jobs.py
deciphon_api/api/prods.py
deciphon_api/api/responses.py
deciphon_api/api/scans.py
deciphon_api/api/sched.py
deciphon_api/api/seqs.py
deciphon_api/console.py
deciphon_api/core/__init__.py
deciphon_api/core/errors.py
deciphon_api/core/events.py
deciphon_api/core/logging.py
deciphon_api/core/rc.py
deciphon_api/core/responses.py
deciphon_api/core/settings.py
deciphon_api/data.py
deciphon_api/main.py
deciphon_api/models/__init__.py
deciphon_api/models/db.py
deciphon_api/models/hmm.py
deciphon_api/models/job.py
deciphon_api/models/prod.py
deciphon_api/models/scan.py
deciphon_api/models/scan_result.py
deciphon_api/models/sched_health.py
deciphon_api/models/seq.py
deciphon_api/resources/.env.example
deciphon_api/resources/__init__.py
deciphon_api/resources/prods_as_amino.fasta
deciphon_api/resources/prods_as_codon.fasta
deciphon_api/resources/prods_as_fragment.fasta
deciphon_api/resources/prods_as_gff.gff
deciphon_api/resources/prods_as_path.fasta
deciphon_api/resources/prods_file.tsv
deciphon_api/sched/__init__.py
deciphon_api/sched/cffi.cpython-38-darwin.so
deciphon_api/sched/cffi.cpython-39-darwin.so
deciphon_api/sched/db.py
deciphon_api/sched/error.py
deciphon_api/sched/hmm.py
deciphon_api/sched/interface.h
deciphon_api/sched/interface_preamble.h
deciphon_api/sched/job.py
deciphon_api/sched/prod.py
deciphon_api/sched/rc.py
deciphon_api/sched/scan.py
deciphon_api/sched/sched.py
deciphon_api/sched/seq.py
deciphon_api-0.3.2.dist-info/entry_points.txt
deciphon_api-0.3.2.dist-info/LICENSE
deciphon_api-0.3.2.dist-info/WHEEL
deciphon_api-0.3.2.dist-info/METADATA
deciphon_api-0.3.2.dist-info/RECORD
