Metadata-Version: 2.1
Name: deciphon-api
Version: 0.3.2
Summary: RESTful API for Deciphon scheduler
Home-page: https://github.com/EBI-Metagenomics/deciphon-api
License: MIT
Keywords: deciphon,api
Author: Danilo Horta
Author-email: danilo.horta@pm.me
Requires-Python: >=3.8,<4.0
Classifier: License :: OSI Approved :: MIT License
Classifier: Programming Language :: Python :: 3
Classifier: Programming Language :: Python :: 3.10
Classifier: Programming Language :: Python :: 3.8
Classifier: Programming Language :: Python :: 3.9
Requires-Dist: bcbio-gff
Requires-Dist: biopython
Requires-Dist: build
Requires-Dist: cffi
Requires-Dist: fastapi
Requires-Dist: loguru
Requires-Dist: pooch
Requires-Dist: pydantic[dotenv]
Requires-Dist: python-multipart
Requires-Dist: toml (>=0.9,<0.10)
Requires-Dist: typer
Requires-Dist: uvicorn[httptools,uvloop]
Requires-Dist: xxhash
Project-URL: Repository, https://github.com/EBI-Metagenomics/deciphon-api
